do_circuit_breaker/__init__.py
do_circuit_breaker/circuit_breaker.py
do_circuit_breaker/circuit_breaker_operator.py
do_circuit_breaker/do_circuit_breaker.py
do_circuit_breaker-0.1.2.dist-info/LICENSE
do_circuit_breaker-0.1.2.dist-info/METADATA
do_circuit_breaker-0.1.2.dist-info/WHEEL
do_circuit_breaker-0.1.2.dist-info/top_level.txt
do_circuit_breaker-0.1.2.dist-info/RECORD
